CGATReport/Cache.py
CGATReport/Component.py
CGATReport/Config.py
CGATReport/CorrespondenceAnalysis.py
CGATReport/DataTree.py
CGATReport/DataTypes.py
CGATReport/Dispatcher.py
CGATReport/Histogram.py
CGATReport/Logger.py
CGATReport/Logger_test.py
CGATReport/ResultBlock.py
CGATReport/SQLDatabase.py
CGATReport/Stats.py
CGATReport/Tracker.py
CGATReport/Utils.py
CGATReport/__init__.py
CGATReport/build.py
CGATReport/clean.py
CGATReport/errors_directive.py
CGATReport/gallery.py
CGATReport/get.py
CGATReport/only_directives.py
CGATReport/profile.py
CGATReport/quickstart.py
CGATReport/report_directive.py
CGATReport/roles.py
CGATReport/serve.py
CGATReport/test.py
CGATReport/warnings_directive.py
CGATReport/images/fail.png
CGATReport/images/not_available.png
CGATReport/images/pass.png
CGATReport/images/warning.png
CGATReport/templates/Discussion.rst
CGATReport/templates/Introduction.rst
CGATReport/templates/Makefile
CGATReport/templates/Methods.rst
CGATReport/templates/PipelineTest.rst
CGATReport/templates/Results.rst
CGATReport/templates/Trackers.py
CGATReport/templates/Trackers.rst
CGATReport/templates/analysis.rst
CGATReport/templates/cgat.css_t
CGATReport/templates/cgatreport.ini
CGATReport/templates/conf.py
CGATReport/templates/contents.rst
CGATReport/templates/data_table.html
CGATReport/templates/gallery.html
CGATReport/templates/index.html
CGATReport/templates/indexsidebar.html
CGATReport/templates/labbook.css
CGATReport/templates/layout.html
CGATReport/templates/pipeline.rst
CGATReport/templates/search.html
CGATReport/templates/server.py
CGATReport/templates/theme.conf
CGATReport/templates/usage.rst
CGATReport/templates/js/jquery-1.9.1.min.js
CGATReport/templates/js/jquery.dataTables.min.js
CGATReport/templates/js/jquery.min.js
CGATReport/templates/js/jssor.js
CGATReport/templates/js/jssor.player.ytiframe.compress.bat
CGATReport/templates/js/jssor.player.ytiframe.js
CGATReport-0.3.dist-info/DESCRIPTION.rst
CGATReport-0.3.dist-info/METADATA
CGATReport-0.3.dist-info/RECORD
CGATReport-0.3.dist-info/WHEEL
CGATReport-0.3.dist-info/entry_points.txt
CGATReport-0.3.dist-info/metadata.json
CGATReport-0.3.dist-info/top_level.txt
