Metadata-Version: 2.0
Name: CGATReport
Version: 0.3
Summary: CGATReport : a report generator in python based on sphinx
Home-page: https://github.com/AndreasHeger/CGATReport/
Author: Andreas Heger
Author-email: andreas.heger@gmail.com
License: BSD
Keywords: report generator sphinx matplotlib sql
Platform: any
Classifier: Development Status :: 4 - Beta
Classifier: Intended Audience :: Science/Research
Classifier: Intended Audience :: Developers
Classifier: License :: OSI Approved
Classifier: Programming Language :: Python
Classifier: Topic :: Software Development
Classifier: Topic :: Scientific/Engineering
Classifier: Operating System :: Microsoft :: Windows
Classifier: Operating System :: POSIX
Classifier: Operating System :: Unix
Classifier: Operating System :: MacOS
Requires-Dist: ggplot (>=0.6.8)
Requires-Dist: matplotlib (>=1.3.1)
Requires-Dist: matplotlib-venn (>=0.5)
Requires-Dist: matplotlib-venn (>=0.5)
Requires-Dist: mpld3 (>=0.2)
Requires-Dist: numpy (>=1.7)
Requires-Dist: openpyxl (>=2.0.3)
Requires-Dist: pandas (>=0.16.0)
Requires-Dist: patsy (>=0.2.1)
Requires-Dist: pillow (>=2.7.0)
Requires-Dist: scipy (>=0.11)
Requires-Dist: seaborn (>=0.3.1)
Requires-Dist: setuptools (>=1.1)
Requires-Dist: sphinx (>=1.0.5)
Requires-Dist: sphinxcontrib-programoutput (>=0.8)
Requires-Dist: sqlalchemy (>=0.7.0)
Requires-Dist: statsmodels (>=0.5.0)
Requires-Dist: web.py (>=0.37)
Requires-Dist: xlwt (>=0.7.4)
Requires-Dist: xlwt (>=0.7.4)
